README.md
setup.py
pip_module/__init__.py
pip_module/xst.py
pip_module_xst.egg-info/PKG-INFO
pip_module_xst.egg-info/SOURCES.txt
pip_module_xst.egg-info/dependency_links.txt
pip_module_xst.egg-info/requires.txt
pip_module_xst.egg-info/top_level.txt